mail_deduplicate/__init__.py
mail_deduplicate/__main__.py
mail_deduplicate/action.py
mail_deduplicate/cli.py
mail_deduplicate/deduplicate.py
mail_deduplicate/mail.py
mail_deduplicate/mail_box.py
mail_deduplicate/py.typed
mail_deduplicate/strategy.py
mail_deduplicate-7.6.2.dist-info/METADATA
mail_deduplicate-7.6.2.dist-info/WHEEL
mail_deduplicate-7.6.2.dist-info/entry_points.txt
mail_deduplicate-7.6.2.dist-info/top_level.txt
mail_deduplicate-7.6.2.dist-info/RECORD
