Metadata-Version: 2.4
Name: mail-deduplicate
Version: 7.6.2
Summary: 📧 CLI to deduplicate mails from mail boxes
Author-email: Kevin Deldycke <kevin@deldycke.com>
Project-URL: Homepage, https://github.com/kdeldycke/mail-deduplicate
Project-URL: Documentation, https://kdeldycke.github.io/mail-deduplicate
Project-URL: Repository, https://github.com/kdeldycke/mail-deduplicate
Project-URL: Funding, https://github.com/sponsors/kdeldycke
Project-URL: Issues, https://github.com/kdeldycke/mail-deduplicate/issues
Project-URL: Changelog, https://github.com/kdeldycke/mail-deduplicate/blob/main/changelog.md
Keywords: CLI,mail,email,maildir,mbox,deduplication,dedupe,cleanup,mailbox,Babyl,MH,mbox,MMDF
Classifier: Development Status :: 5 - Production/Stable
Classifier: Environment :: Console
Classifier: Intended Audience :: Developers
Classifier: Intended Audience :: Information Technology
Classifier: License :: OSI Approved :: GNU General Public License v2 or later (GPLv2+)
Classifier: Operating System :: MacOS
Classifier: Operating System :: Microsoft :: Windows
Classifier: Operating System :: POSIX
Classifier: Programming Language :: Python :: 3
Classifier: Programming Language :: Python :: 3.10
Classifier: Programming Language :: Python :: 3.11
Classifier: Programming Language :: Python :: 3.12
Classifier: Programming Language :: Python :: 3.13
Classifier: Programming Language :: Python :: Implementation :: CPython
Classifier: Topic :: Communications :: Email
Classifier: Topic :: Utilities
Classifier: Typing :: Typed
Requires-Python: >=3.10
Requires-Dist: arrow~=1.3.0
Requires-Dist: boltons~=25.0.0
Requires-Dist: click-extra~=4.15.0
Requires-Dist: tabulate[widechars]~=0.9
Provides-Extra: test
Requires-Dist: click-extra[pytest]~=4.15.0; extra == "test"
Requires-Dist: coverage[toml]~=7.6.7; extra == "test"
Requires-Dist: extra-platforms[pytest]~=2.1.0; extra == "test"
Requires-Dist: pytest~=8.3.3; extra == "test"
Requires-Dist: pytest-cov~=6.0.0; extra == "test"
Requires-Dist: pytest-github-actions-annotate-failures~=0.2.0; extra == "test"
Requires-Dist: pytest-randomly~=3.16.0; extra == "test"
Provides-Extra: typing
Requires-Dist: types-tabulate~=0.9.0.2; extra == "typing"
Provides-Extra: docs
Requires-Dist: click-extra[sphinx]~=4.15.0; extra == "docs"
Requires-Dist: furo~=2024.8.6; extra == "docs"
Requires-Dist: myst-parser~=4.0.0; extra == "docs"
Requires-Dist: sphinx~=8.1.3; extra == "docs"
Requires-Dist: sphinx-autodoc-typehints~=2.5.0; extra == "docs"
Requires-Dist: sphinx-click~=6.0.0; extra == "docs"
Requires-Dist: sphinx-copybutton~=0.5.2; extra == "docs"
Requires-Dist: sphinx-design~=0.6.0; extra == "docs"
Requires-Dist: sphinx-issues~=5.0.0; extra == "docs"
Requires-Dist: sphinxcontrib-mermaid~=1.0.0; extra == "docs"
Requires-Dist: sphinxext-opengraph~=0.9.0; extra == "docs"
Requires-Dist: tomli~=2.0.1; python_version < "3.11" and extra == "docs"
